{"current":{"temp":8,"condition":"Lightrain","icon":"wi-day-sprinkle","is_precip":true,"wind_speed":17,"wind_dir":"E","humidity":94,"symbol":"lightrain"},"hourly":[{"time_iso":"2026-05-16T11:00:00Z","temp":8,"icon":"wi-day-sprinkle","is_precip":true,"precip_mm":0.2,"precip_bar":4,"wind_speed":17,"wind_dir":"E","humidity":94,"symbol":"lightrain"},{"time_iso":"2026-05-16T12:00:00Z","temp":7,"icon":"wi-day-sprinkle","is_precip":true,"precip_mm":0.2,"precip_bar":4,"wind_speed":18,"wind_dir":"E","humidity":93,"symbol":"lightrain"},{"time_iso":"2026-05-16T13:00:00Z","temp":7,"icon":"wi-day-sprinkle","is_precip":true,"precip_mm":0.2,"precip_bar":4,"wind_speed":14,"wind_dir":"E","humidity":90,"symbol":"lightrain"},{"time_iso":"2026-05-16T14:00:00Z","temp":7,"icon":"wi-cloudy","is_precip":false,"precip_mm":0,"precip_bar":0,"wind_speed":13,"wind_dir":"E","humidity":86,"symbol":"cloudy"},{"time_iso":"2026-05-16T15:00:00Z","temp":8,"icon":"wi-day-cloudy","is_precip":false,"precip_mm":0,"precip_bar":0,"wind_speed":13,"wind_dir":"E","humidity":84,"symbol":"partlycloudy_day"},{"time_iso":"2026-05-16T16:00:00Z","temp":8,"icon":"wi-day-cloudy","is_precip":false,"precip_mm":0,"precip_bar":0,"wind_speed":9,"wind_dir":"SE","humidity":80,"symbol":"partlycloudy_day"},{"time_iso":"2026-05-16T17:00:00Z","temp":10,"icon":"wi-day-cloudy","is_precip":false,"precip_mm":0,"precip_bar":0,"wind_speed":6,"wind_dir":"SW","humidity":72,"symbol":"partlycloudy_day"},{"time_iso":"2026-05-16T18:00:00Z","temp":10,"icon":"wi-day-sunny","is_precip":false,"precip_mm":0,"precip_bar":0,"wind_speed":14,"wind_dir":"W","humidity":70,"symbol":"fair_day"},{"time_iso":"2026-05-16T19:00:00Z","temp":11,"icon":"wi-day-sunny","is_precip":false,"precip_mm":0,"precip_bar":0,"wind_speed":21,"wind_dir":"W","humidity":70,"symbol":"fair_day"},{"time_iso":"2026-05-16T20:00:00Z","temp":12,"icon":"wi-day-sunny","is_precip":false,"precip_mm":0,"precip_bar":0,"wind_speed":22,"wind_dir":"NW","humidity":70,"symbol":"fair_day"},{"time_iso":"2026-05-16T21:00:00Z","temp":12,"icon":"wi-day-sunny","is_precip":false,"precip_mm":0,"precip_bar":0,"wind_speed":23,"wind_dir":"W","humidity":66,"symbol":"fair_day"},{"time_iso":"2026-05-16T22:00:00Z","temp":13,"icon":"wi-day-sunny","is_precip":false,"precip_mm":0,"precip_bar":0,"wind_speed":27,"wind_dir":"W","humidity":68,"symbol":"fair_day"},{"time_iso":"2026-05-16T23:00:00Z","temp":13,"icon":"wi-day-cloudy","is_precip":false,"precip_mm":0,"precip_bar":0,"wind_speed":26,"wind_dir":"W","humidity":66,"symbol":"partlycloudy_day"},{"time_iso":"2026-05-17T00:00:00Z","temp":12,"icon":"wi-day-cloudy","is_precip":false,"precip_mm":0,"precip_bar":0,"wind_speed":25,"wind_dir":"SW","humidity":66,"symbol":"partlycloudy_day"},{"time_iso":"2026-05-17T01:00:00Z","temp":12,"icon":"wi-day-cloudy","is_precip":false,"precip_mm":0,"precip_bar":0,"wind_speed":24,"wind_dir":"W","humidity":65,"symbol":"partlycloudy_day"},{"time_iso":"2026-05-17T02:00:00Z","temp":12,"icon":"wi-day-cloudy","is_precip":false,"precip_mm":0,"precip_bar":0,"wind_speed":26,"wind_dir":"W","humidity":62,"symbol":"partlycloudy_day"},{"time_iso":"2026-05-17T03:00:00Z","temp":13,"icon":"wi-day-sunny","is_precip":false,"precip_mm":0,"precip_bar":0,"wind_speed":26,"wind_dir":"W","humidity":61,"symbol":"fair_day"},{"time_iso":"2026-05-17T04:00:00Z","temp":12,"icon":"wi-night-alt-partly-cloudy","is_precip":false,"precip_mm":0,"precip_bar":0,"wind_speed":27,"wind_dir":"NW","humidity":65,"symbol":"partlycloudy_night"},{"time_iso":"2026-05-17T05:00:00Z","temp":12,"icon":"wi-night-clear","is_precip":false,"precip_mm":0,"precip_bar":0,"wind_speed":23,"wind_dir":"NW","humidity":67,"symbol":"clearsky_night"},{"time_iso":"2026-05-17T06:00:00Z","temp":12,"icon":"wi-night-alt-partly-cloudy","is_precip":false,"precip_mm":0,"precip_bar":0,"wind_speed":16,"wind_dir":"NW","humidity":73,"symbol":"partlycloudy_night"},{"time_iso":"2026-05-17T07:00:00Z","temp":11,"icon":"wi-night-alt-partly-cloudy","is_precip":false,"precip_mm":0,"precip_bar":0,"wind_speed":16,"wind_dir":"NE","humidity":77,"symbol":"partlycloudy_night"},{"time_iso":"2026-05-17T08:00:00Z","temp":10,"icon":"wi-night-clear","is_precip":false,"precip_mm":0,"precip_bar":0,"wind_speed":17,"wind_dir":"E","humidity":86,"symbol":"fair_night"},{"time_iso":"2026-05-17T09:00:00Z","temp":9,"icon":"wi-night-clear","is_precip":false,"precip_mm":0,"precip_bar":0,"wind_speed":17,"wind_dir":"E","humidity":91,"symbol":"fair_night"},{"time_iso":"2026-05-17T10:00:00Z","temp":9,"icon":"wi-night-clear","is_precip":false,"precip_mm":0,"precip_bar":0,"wind_speed":14,"wind_dir":"E","humidity":93,"symbol":"fair_night"}],"daily":[{"day":"Sat","date":"2026-05-16","high":7,"icon":"wi-day-sprinkle","is_precip":true,"symbol":"lightrainshowers_day"},{"day":"Sun","date":"2026-05-17","high":9,"icon":"wi-day-cloudy","is_precip":false,"symbol":"partlycloudy_day","low":12},{"day":"Mon","date":"2026-05-18","high":11,"icon":"wi-cloudy","is_precip":false,"symbol":"cloudy","low":15},{"day":"Tue","date":"2026-05-19","high":10,"icon":"wi-day-sunny","is_precip":false,"symbol":"fair_day","low":16},{"day":"Wed","date":"2026-05-20","high":12,"icon":"wi-cloudy","is_precip":false,"symbol":"cloudy","low":16},{"day":"Thu","date":"2026-05-21","high":11,"icon":"wi-cloudy","is_precip":false,"symbol":"cloudy","low":17},{"day":"Fri","date":"2026-05-22","high":11,"icon":"wi-day-sunny","is_precip":false,"symbol":"fair_day","low":16}],"lat":49.154,"lon":-123.158,"updated":"2026-05-16 11:45 UTC"}